odoo/addons/purchase_receipt_expectation_from_partner/README.rst
odoo/addons/purchase_receipt_expectation_from_partner/__init__.py
odoo/addons/purchase_receipt_expectation_from_partner/__manifest__.py
odoo/addons/purchase_receipt_expectation_from_partner/i18n/fr.po
odoo/addons/purchase_receipt_expectation_from_partner/i18n/purchase_receipt_expectation_from_partner.pot
odoo/addons/purchase_receipt_expectation_from_partner/models/__init__.py
odoo/addons/purchase_receipt_expectation_from_partner/models/purchase_order.py
odoo/addons/purchase_receipt_expectation_from_partner/models/res_partner.py
odoo/addons/purchase_receipt_expectation_from_partner/readme/CONTRIBUTORS.rst
odoo/addons/purchase_receipt_expectation_from_partner/readme/DESCRIPTION.rst
odoo/addons/purchase_receipt_expectation_from_partner/readme/USAGE.rst
odoo/addons/purchase_receipt_expectation_from_partner/static/description/icon.png
odoo/addons/purchase_receipt_expectation_from_partner/static/description/index.html
odoo/addons/purchase_receipt_expectation_from_partner/tests/__init__.py
odoo/addons/purchase_receipt_expectation_from_partner/tests/test_purchase_receipt_expectation_from_partner.py
odoo/addons/purchase_receipt_expectation_from_partner/views/res_partner.xml
odoo_addon_purchase_receipt_expectation_from_partner-15.0.1.0.0.7.dist-info/METADATA
odoo_addon_purchase_receipt_expectation_from_partner-15.0.1.0.0.7.dist-info/WHEEL
odoo_addon_purchase_receipt_expectation_from_partner-15.0.1.0.0.7.dist-info/top_level.txt
odoo_addon_purchase_receipt_expectation_from_partner-15.0.1.0.0.7.dist-info/RECORD
