Metadata-Version: 2.1
Name: odoo-addon-purchase-receipt-expectation-from-partner
Version: 15.0.1.0.0.7
Summary: Purchase Receipt Expectation From Partner
Home-page: https://github.com/OCA/purchase-workflow
Author: Camptocamp SA, Odoo Community Association (OCA)
Author-email: support@odoo-community.org
License: AGPL-3
Platform: UNKNOWN
Classifier: Programming Language :: Python
Classifier: Framework :: Odoo
Classifier: Framework :: Odoo :: 15.0
Classifier: License :: OSI Approved :: GNU Affero General Public License v3
Requires-Python: >=3.8
Requires-Dist: odoo-addon-purchase-receipt-expectation <15.1dev,>=15.0dev
Requires-Dist: odoo <15.1dev,>=15.0a
